example_package_flower_test/__init__.py
example_package_flower_test/example.py
example_package_flower-0.0.1.dist-info/LICENSE
example_package_flower-0.0.1.dist-info/METADATA
example_package_flower-0.0.1.dist-info/WHEEL
example_package_flower-0.0.1.dist-info/top_level.txt
example_package_flower-0.0.1.dist-info/RECORD
