Metadata-Version: 2.1
Name: example-package-flower
Version: 0.0.1
Summary: A small example package
Home-page: https://github.com/asmexcaliburwoods/pylibsampleproject
Author: flower
Author-email: egphilippov@gmail.com
License: UNKNOWN
Project-URL: Bug Tracker, https://github.com/asmexcaliburwoods/pylibsampleproject/issues
Project-URL: Flower Growth Extension Site, https://github.com/asmexcaliburwoods
Project-URL: PyPi Profile, https://pypi.org/user/flower/
Platform: UNKNOWN
Classifier: Programming Language :: Python :: 3
Classifier: License :: OSI Approved :: GNU Lesser General Public License v3 or later (LGPLv3+)
Classifier: Operating System :: OS Independent
Requires-Python: >=3.6
License-File: LICENSE
